kirigami/__about__.py
kirigami/__init__.py
kirigami/__main__.py
kirigami/cli.py
kirigami-0.0.2.dist-info/METADATA
kirigami-0.0.2.dist-info/WHEEL
kirigami-0.0.2.dist-info/licenses/LICENSE
kirigami-0.0.2.dist-info/RECORD
